Akuanduba/__init__.py
Akuanduba/core/Akuanduba.py
Akuanduba/core/Context.py
Akuanduba/core/CoreClasses.py
Akuanduba/core/EventStatus.py
Akuanduba/core/Manager.py
Akuanduba/core/StatusCode.py
Akuanduba/core/Trigger.py
Akuanduba/core/Watchdog.py
Akuanduba/core/__init__.py
Akuanduba/core/constants.py
Akuanduba/core/gtypes.py
Akuanduba/core/utilities.py
Akuanduba/core/messenger/Logger.py
Akuanduba/core/messenger/__init__.py
Akuanduba/core/messenger/macros.py
Akuanduba/dataframe/__init__.py
Akuanduba/services/NTPSyncService.py
Akuanduba/services/StoreGateSvc.py
Akuanduba/services/__init__.py
Akuanduba/tools/DataLog.py
Akuanduba/tools/__init__.py
Akuanduba/triggers/TimerCondition.py
Akuanduba/triggers/__init__.py
Akuanduba-0.2.1.dist-info/LICENSE
Akuanduba-0.2.1.dist-info/LICENSE.txt
Akuanduba-0.2.1.dist-info/METADATA
Akuanduba-0.2.1.dist-info/WHEEL
Akuanduba-0.2.1.dist-info/top_level.txt
Akuanduba-0.2.1.dist-info/RECORD
