Metadata-Version: 2.1
Name: Akuanduba
Version: 0.2.1
Summary: Akuanduba is a Python framework that eases manipulation of multiple running threads and shared resources. Its name was inspired by a god of the Brazilian mythology: Akuanduba, the god of order.
Home-page: https://github.com/gabriel-milan/Akuanduba
Author: Gabriel Gazola Milan
Author-email: gabriel.gazola@poli.ufrj.br
License: GPL-3.0
Keywords: framework,threading,shared resources,flexibility,python,online
Platform: UNKNOWN
Classifier: Development Status :: 4 - Beta
Classifier: Intended Audience :: Developers
Classifier: Topic :: Software Development :: Libraries :: Python Modules
Classifier: License :: OSI Approved :: GNU General Public License v3 (GPLv3)
Classifier: Programming Language :: Python :: 3
Classifier: Programming Language :: Python :: 3.4
Classifier: Programming Language :: Python :: 3.5
Classifier: Programming Language :: Python :: 3.6
Classifier: Programming Language :: Python :: 3.7
Requires-Dist: datetime
Requires-Dist: pytz
